te/__info__.py
te/__init__.py
te/__main__.py
te-1.0.1.dist-info/LICENSE
te-1.0.1.dist-info/METADATA
te-1.0.1.dist-info/WHEEL
te-1.0.1.dist-info/entry_points.txt
te-1.0.1.dist-info/top_level.txt
te-1.0.1.dist-info/RECORD
