Metadata-Version: 2.1
Name: te
Version: 1.0.1
Summary: Toggl Entry - CLI REST API client for Toggl
Home-page: https://github.com/hubpav/te
Author: Pavel Hübner
Author-email: pavel.hubner@gmail.com
License: MIT
Keywords: toggl cli timesheet entry time tracking
Platform: any
Classifier: Development Status :: 5 - Production/Stable
Classifier: Environment :: Console
Classifier: Intended Audience :: Developers
Classifier: License :: OSI Approved :: MIT License
Classifier: Natural Language :: English
Classifier: Operating System :: OS Independent
Classifier: Programming Language :: Python :: 3
Classifier: Topic :: Utilities
Requires-Dist: certifi (==2019.11.28)
Requires-Dist: chardet (==3.0.4)
Requires-Dist: Click (==7.0)
Requires-Dist: idna (==2.8)
Requires-Dist: pendulum (==2.0.5)
Requires-Dist: python-dateutil (==2.8.1)
Requires-Dist: pytzdata (==2019.3)
Requires-Dist: requests (==2.22.0)
Requires-Dist: six (==1.13.0)
Requires-Dist: urllib3 (==1.25.7)
